README.rst
setup.py
make_it_easy/__init__.py
make_it_easy/make_it_easy.py
make_it_easy.egg-info/PKG-INFO
make_it_easy.egg-info/SOURCES.txt
make_it_easy.egg-info/dependency_links.txt
make_it_easy.egg-info/top_level.txt