Metadata-Version: 1.1
Name: make-it-easy
Version: 1.0.1
Summary: A tiny framework that makes it easy to write Test Data Builders in Python
Home-page: https://www.github.com/dorireuv/make-it-easy
Author: Dori Reuveni
Author-email: dorireuv@gmail.com
License: Apache License (2.0)
Keywords: testing,test,tdd,unittest,builder,goos
Platform: UNKNOWN
Classifier: Programming Language :: Python
Classifier: Programming Language :: Python :: 2
Classifier: Programming Language :: Python :: 2.6
Classifier: Programming Language :: Python :: 2.7
Classifier: Programming Language :: Python :: 3
Classifier: Programming Language :: Python :: 3.2
Classifier: Programming Language :: Python :: 3.3
Classifier: Operating System :: OS Independent
Classifier: Intended Audience :: Developers
Classifier: Development Status :: 5 - Production/Stable
Classifier: Topic :: Software Development :: Libraries
Classifier: Topic :: Software Development :: Libraries :: Python Modules
Classifier: Topic :: Software Development :: Testing
Classifier: License :: OSI Approved :: Apache Software License
